wavelink/__init__.py
wavelink/__main__.py
wavelink/backoff.py
wavelink/enums.py
wavelink/exceptions.py
wavelink/filters.py
wavelink/lfu.py
wavelink/node.py
wavelink/payloads.py
wavelink/player.py
wavelink/py.typed
wavelink/queue.py
wavelink/tracks.py
wavelink/utils.py
wavelink/websocket.py
wavelink/types/__init__.py
wavelink/types/filters.py
wavelink/types/request.py
wavelink/types/response.py
wavelink/types/state.py
wavelink/types/stats.py
wavelink/types/tracks.py
wavelink/types/websocket.py
wavelink-3.4.1.dist-info/LICENSE
wavelink-3.4.1.dist-info/METADATA
wavelink-3.4.1.dist-info/WHEEL
wavelink-3.4.1.dist-info/top_level.txt
wavelink-3.4.1.dist-info/RECORD
